{
  "name": "Elegant",
  "colors": [
    {
      "name": "Bright Black",
      "hex": "#575656"
    },
    {
      "name": "Black",
      "hex": "#0a1222"
    },
    {
      "name": "Bright Blue",
      "hex": "#8dabe1"
    },
    {
      "name": "Blue",
      "hex": "#8dabe1"
    },
    {
      "name": "Bright Cyan",
      "hex": "#3facef"
    },
    {
      "name": "Cyan",
      "hex": "#78ccf0"
    },
    {
      "name": "Bright Green",
      "hex": "#85cc95"
    },
    {
      "name": "Green",
      "hex": "#85cc95"
    },
    {
      "name": "Bright Magenta",
      "hex": "#c792eb"
    },
    {
      "name": "Magenta",
      "hex": "#c792eb"
    },
    {
      "name": "Bright Red",
      "hex": "#ff0057"
    },
    {
      "name": "Red",
      "hex": "#ff0257"
    },
    {
      "name": "Bright White",
      "hex": "#ffffff"
    },
    {
      "name": "White",
      "hex": "#ffffff"
    },
    {
      "name": "Bright Yellow",
      "hex": "#ffcb8b"
    },
    {
      "name": "Yellow",
      "hex": "#ffcb8b"
    },
    {
      "name": "Selection",
      "hex": "#d5d5d5"
    },
    {
      "name": "Selection Text",
      "hex": "#144385"
    },
    {
      "name": "Cursor",
      "hex": "#00beff"
    },
    {
      "name": "Cursor Text",
      "hex": "#ffffff"
    },
    {
      "name": "Foreground",
      "hex": "#ced2d6"
    },
    {
      "name": "Background",
      "hex": "#292b31"
    }
  ]
}
