{
  "name": "Jackie Brown",
  "colors": [
    {
      "name": "Bright Black",
      "hex": "#666666"
    },
    {
      "name": "Black",
      "hex": "#2c1d16"
    },
    {
      "name": "Bright Blue",
      "hex": "#0000ff"
    },
    {
      "name": "Blue",
      "hex": "#246eb2"
    },
    {
      "name": "Bright Cyan",
      "hex": "#00e5e5"
    },
    {
      "name": "Cyan",
      "hex": "#00acee"
    },
    {
      "name": "Bright Green",
      "hex": "#86a93e"
    },
    {
      "name": "Green",
      "hex": "#2baf2b"
    },
    {
      "name": "Bright Magenta",
      "hex": "#e500e5"
    },
    {
      "name": "Magenta",
      "hex": "#d05ec1"
    },
    {
      "name": "Bright Red",
      "hex": "#e50000"
    },
    {
      "name": "Red",
      "hex": "#ef5734"
    },
    {
      "name": "Bright White",
      "hex": "#e5e5e5"
    },
    {
      "name": "White",
      "hex": "#bfbfbf"
    },
    {
      "name": "Bright Yellow",
      "hex": "#e5e500"
    },
    {
      "name": "Yellow",
      "hex": "#bebf00"
    },
    {
      "name": "Selection",
      "hex": "#af8d21"
    },
    {
      "name": "Selection Text",
      "hex": "#ffffff"
    },
    {
      "name": "Cursor",
      "hex": "#23ff18"
    },
    {
      "name": "Cursor Text",
      "hex": "#ff0018"
    },
    {
      "name": "Foreground",
      "hex": "#ffcc2f"
    },
    {
      "name": "Background",
      "hex": "#2c1d16"
    }
  ]
}
