{
  "name": "Paul Millr",
  "colors": [
    {
      "name": "Bright Black",
      "hex": "#666666"
    },
    {
      "name": "Black",
      "hex": "#2a2a2a"
    },
    {
      "name": "Bright Blue",
      "hex": "#709aed"
    },
    {
      "name": "Blue",
      "hex": "#396bd7"
    },
    {
      "name": "Bright Cyan",
      "hex": "#7adff2"
    },
    {
      "name": "Cyan",
      "hex": "#66ccff"
    },
    {
      "name": "Bright Green",
      "hex": "#66ff66"
    },
    {
      "name": "Green",
      "hex": "#79ff0f"
    },
    {
      "name": "Bright Magenta",
      "hex": "#db67e6"
    },
    {
      "name": "Magenta",
      "hex": "#b449be"
    },
    {
      "name": "Bright Red",
      "hex": "#ff0080"
    },
    {
      "name": "Red",
      "hex": "#ff0000"
    },
    {
      "name": "Bright White",
      "hex": "#ffffff"
    },
    {
      "name": "White",
      "hex": "#bbbbbb"
    },
    {
      "name": "Bright Yellow",
      "hex": "#f3d64e"
    },
    {
      "name": "Yellow",
      "hex": "#e7bf00"
    },
    {
      "name": "Selection",
      "hex": "#414141"
    },
    {
      "name": "Selection Text",
      "hex": "#ffffff"
    },
    {
      "name": "Cursor",
      "hex": "#4d4d4d"
    },
    {
      "name": "Cursor Text",
      "hex": "#ffffff"
    },
    {
      "name": "Foreground",
      "hex": "#f2f2f2"
    },
    {
      "name": "Background",
      "hex": "#000000"
    }
  ]
}
