{
  "name": "Piatto Light",
  "colors": [
    {
      "name": "Bright Black",
      "hex": "#3f3f3f"
    },
    {
      "name": "Black",
      "hex": "#414141"
    },
    {
      "name": "Bright Blue",
      "hex": "#3c5ea8"
    },
    {
      "name": "Blue",
      "hex": "#3c5ea8"
    },
    {
      "name": "Bright Cyan",
      "hex": "#829429"
    },
    {
      "name": "Cyan",
      "hex": "#66781e"
    },
    {
      "name": "Bright Green",
      "hex": "#829429"
    },
    {
      "name": "Green",
      "hex": "#66781e"
    },
    {
      "name": "Bright Magenta",
      "hex": "#a454b2"
    },
    {
      "name": "Magenta",
      "hex": "#a454b2"
    },
    {
      "name": "Bright Red",
      "hex": "#db3365"
    },
    {
      "name": "Red",
      "hex": "#b23771"
    },
    {
      "name": "Bright White",
      "hex": "#f2f2f2"
    },
    {
      "name": "White",
      "hex": "#bfbfbf"
    },
    {
      "name": "Bright Yellow",
      "hex": "#cd6f34"
    },
    {
      "name": "Yellow",
      "hex": "#cd6f34"
    },
    {
      "name": "Selection",
      "hex": "#706b4e"
    },
    {
      "name": "Selection Text",
      "hex": "#acbcdc"
    },
    {
      "name": "Cursor",
      "hex": "#5e77c8"
    },
    {
      "name": "Cursor Text",
      "hex": "#abbee5"
    },
    {
      "name": "Foreground",
      "hex": "#414141"
    },
    {
      "name": "Background",
      "hex": "#ffffff"
    }
  ]
}
