{
  "name": "Red Planet",
  "colors": [
    {
      "name": "Bright Black",
      "hex": "#676767"
    },
    {
      "name": "Black",
      "hex": "#202020"
    },
    {
      "name": "Bright Blue",
      "hex": "#60827e"
    },
    {
      "name": "Blue",
      "hex": "#69819e"
    },
    {
      "name": "Bright Cyan",
      "hex": "#38add8"
    },
    {
      "name": "Cyan",
      "hex": "#5b8390"
    },
    {
      "name": "Bright Green",
      "hex": "#869985"
    },
    {
      "name": "Green",
      "hex": "#728271"
    },
    {
      "name": "Bright Magenta",
      "hex": "#de4974"
    },
    {
      "name": "Magenta",
      "hex": "#896492"
    },
    {
      "name": "Bright Red",
      "hex": "#b55242"
    },
    {
      "name": "Red",
      "hex": "#8c3432"
    },
    {
      "name": "Bright White",
      "hex": "#d6bfb8"
    },
    {
      "name": "White",
      "hex": "#b9aa99"
    },
    {
      "name": "Bright Yellow",
      "hex": "#ebeb91"
    },
    {
      "name": "Yellow",
      "hex": "#e8bf6a"
    },
    {
      "name": "Selection",
      "hex": "#1b324a"
    },
    {
      "name": "Selection Text",
      "hex": "#bcb291"
    },
    {
      "name": "Cursor",
      "hex": "#c2b790"
    },
    {
      "name": "Cursor Text",
      "hex": "#202020"
    },
    {
      "name": "Foreground",
      "hex": "#c2b790"
    },
    {
      "name": "Background",
      "hex": "#222222"
    }
  ]
}
