{
  "name": "Solarized Darcula",
  "colors": [
    {
      "name": "Bright Black",
      "hex": "#65696a"
    },
    {
      "name": "Black",
      "hex": "#25292a"
    },
    {
      "name": "Bright Blue",
      "hex": "#2075c7"
    },
    {
      "name": "Blue",
      "hex": "#2075c7"
    },
    {
      "name": "Bright Cyan",
      "hex": "#15968d"
    },
    {
      "name": "Cyan",
      "hex": "#15968d"
    },
    {
      "name": "Bright Green",
      "hex": "#629655"
    },
    {
      "name": "Green",
      "hex": "#629655"
    },
    {
      "name": "Bright Magenta",
      "hex": "#797fd4"
    },
    {
      "name": "Magenta",
      "hex": "#797fd4"
    },
    {
      "name": "Bright Red",
      "hex": "#f24840"
    },
    {
      "name": "Red",
      "hex": "#f24840"
    },
    {
      "name": "Bright White",
      "hex": "#d2d8d9"
    },
    {
      "name": "White",
      "hex": "#d2d8d9"
    },
    {
      "name": "Bright Yellow",
      "hex": "#b68800"
    },
    {
      "name": "Yellow",
      "hex": "#b68800"
    },
    {
      "name": "Selection",
      "hex": "#214283"
    },
    {
      "name": "Selection Text",
      "hex": "#d2d8d9"
    },
    {
      "name": "Cursor",
      "hex": "#708284"
    },
    {
      "name": "Cursor Text",
      "hex": "#002831"
    },
    {
      "name": "Foreground",
      "hex": "#d2d8d9"
    },
    {
      "name": "Background",
      "hex": "#3d3f41"
    }
  ]
}
